bcf/__init__.py
bcf/bcfxml.py
bcf/extensions.py
bcf/geometry.py
bcf/inmemory_zipfile.py
bcf/py.typed
bcf/xml_parser.py
bcf/agnostic/extensions.py
bcf/agnostic/model.py
bcf/agnostic/topic.py
bcf/agnostic/visinfo.py
bcf/v2/__init__.py
bcf/v2/bcfxml.py
bcf/v2/topic.py
bcf/v2/visinfo.py
bcf/v2/model/__init__.py
bcf/v2/model/extensions.py
bcf/v2/model/markup.py
bcf/v2/model/project.py
bcf/v2/model/version.py
bcf/v2/model/visinfo.py
bcf/v3/__init__.py
bcf/v3/bcfapi.py
bcf/v3/bcfxml.py
bcf/v3/document.py
bcf/v3/topic.py
bcf/v3/visinfo.py
bcf/v3/model/__init__.py
bcf/v3/model/documents.py
bcf/v3/model/extensions.py
bcf/v3/model/markup.py
bcf/v3/model/project.py
bcf/v3/model/version.py
bcf/v3/model/visinfo.py
bcf_client-0.8.3.dist-info/METADATA
bcf_client-0.8.3.dist-info/WHEEL
bcf_client-0.8.3.dist-info/top_level.txt
bcf_client-0.8.3.dist-info/RECORD
